Metadata-Version: 2.1
Name: python-monitors
Version: 0.1.1
Summary: A pure Python package to monitor formal specifications over temporal sequences
Home-page: http://github.com/doganulus/python-monitors/
Author: Dogan Ulus
Author-email: doganulus@gmail.com
License: GPLv3+
Platform: UNKNOWN
Classifier: Development Status :: 3 - Alpha
Classifier: Intended Audience :: Developers
Classifier: Intended Audience :: Science/Research
Classifier: Topic :: Scientific/Engineering
Classifier: Topic :: Scientific/Engineering :: Mathematics
Classifier: License :: OSI Approved :: GNU General Public License v3 or later (GPLv3+)
Classifier: Programming Language :: Python :: 3
Requires-Python: >=3
Requires-Dist: python-intervals
Requires-Dist: antlr4-python3-runtime
